celldisect/__init__.py
celldisect/_model.py
celldisect/_module.py
celldisect/data.py
celldisect/trainingplan.py
celldisect/tuner_base.py
celldisect/utils.py
celldisect-0.1.4.dist-info/LICENSE
celldisect-0.1.4.dist-info/METADATA
celldisect-0.1.4.dist-info/WHEEL
celldisect-0.1.4.dist-info/RECORD
