Metadata-Version: 2.3
Name: celldisect
Version: 0.1.4
Summary: Cell DISentangled Experts for Covariate counTerfactuals (CellDISECT). Causal generative model designed to disentangle known covariate variations from unknown ones at test time while simultaneously learning to make counterfactual predictions.
License: BSD-3-Clause
Author: Arian Amani
Author-email: aa34@sanger.ac.uk> Stathis Megas <sm58@sanger.ac.uk
Requires-Python: >=3.9,<3.11
Classifier: License :: OSI Approved :: BSD License
Classifier: Programming Language :: Python :: 3
Classifier: Programming Language :: Python :: 3.9
Classifier: Programming Language :: Python :: 3.10
Provides-Extra: docs
Requires-Dist: adjustText
Requires-Dist: anndata (>=0.10.8,<0.10.9)
Requires-Dist: black
Requires-Dist: flake8
Requires-Dist: gdown
Requires-Dist: importlib-metadata
Requires-Dist: ipykernel
Requires-Dist: ipython ; extra == "docs"
Requires-Dist: jax (>=0.4.16,<0.4.24)
Requires-Dist: jaxlib (>=0.4.16,<0.4.24)
Requires-Dist: jupyter
Requires-Dist: lightning (>=2.2.0,<2.3.0)
Requires-Dist: llvmlite (>=0.42,<0.43)
Requires-Dist: nbconvert
Requires-Dist: nbformat
Requires-Dist: nbsphinx ; extra == "docs"
Requires-Dist: nbsphinx-link ; extra == "docs"
Requires-Dist: numpy (>=1.26.3,<1.27.0)
Requires-Dist: pydata-sphinx-theme ; extra == "docs"
Requires-Dist: pytest
Requires-Dist: pytest-cov
Requires-Dist: ray[data,serve,train,tune] (>=2.9.0,<2.10.0)
Requires-Dist: scanpy ; extra == "docs"
Requires-Dist: scanpydoc ; extra == "docs"
Requires-Dist: scib (>=1.1.5,<1.2.0)
Requires-Dist: scib-metrics (>=0.5.1,<0.6.0)
Requires-Dist: scipy (>=1.12.0,<1.13.0)
Requires-Dist: scvi-tools (>=0.20.3,<1.0.0)
Requires-Dist: seaborn
Requires-Dist: sphinx ; extra == "docs"
Requires-Dist: sphinx-autodoc-typehints ; extra == "docs"
Requires-Dist: sphinx-rtd-theme ; extra == "docs"
Requires-Dist: sphinx_gallery ; extra == "docs"
Requires-Dist: toml ; extra == "docs"
Requires-Dist: torch (>=2.1.0,<2.3.0)
Requires-Dist: typing_extensions (>=4.5,<4.6)
Requires-Dist: wandb
Project-URL: Homepage, https://github.com/Lotfollahi-lab/CellDISECT
